hoshizora.cpython-36m-darwin.so
hoshizora-0.0.1a0.dist-info/DESCRIPTION.rst
hoshizora-0.0.1a0.dist-info/METADATA
hoshizora-0.0.1a0.dist-info/RECORD
hoshizora-0.0.1a0.dist-info/WHEEL
hoshizora-0.0.1a0.dist-info/metadata.json
hoshizora-0.0.1a0.dist-info/top_level.txt
