Metadata-Version: 2.0
Name: hoshizora
Version: 0.0.1a0
Summary: Fast graph analysis engine
Home-page: https://github.com/hoshizora-project/hoshizora
Author: amaya
Author-email: mail@sapphire.in.net
License: Apache2.0
Keywords: graph graph-processing graph-analysis
Platform: UNKNOWN
